aiida_tbmodels/__init__.py
aiida_tbmodels/calculations/__init__.py
aiida_tbmodels/calculations/_base.py
aiida_tbmodels/calculations/eigenvals.py
aiida_tbmodels/calculations/parse.py
aiida_tbmodels/calculations/slice.py
aiida_tbmodels/calculations/symmetrize.py
aiida_tbmodels/parsers/__init__.py
aiida_tbmodels/parsers/_base.py
aiida_tbmodels/parsers/model.py
aiida_tbmodels/workflows/__init__.py
aiida_tbmodels/workflows/parse.py
aiida_tbmodels-0.4.0rc2.dist-info/LICENSE.txt
aiida_tbmodels-0.4.0rc2.dist-info/METADATA
aiida_tbmodels-0.4.0rc2.dist-info/WHEEL
aiida_tbmodels-0.4.0rc2.dist-info/entry_points.txt
aiida_tbmodels-0.4.0rc2.dist-info/top_level.txt
aiida_tbmodels-0.4.0rc2.dist-info/RECORD
